pynspawn/__init__.py
pynspawn/pynspawn.py
pynspawn-1.2.1.post5.dist-info/METADATA
pynspawn-1.2.1.post5.dist-info/WHEEL
pynspawn-1.2.1.post5.dist-info/top_level.txt
pynspawn-1.2.1.post5.dist-info/RECORD
